toolsbox/__init__.py
toolsbox/demo/__init__.py
toolsbox/demo/demo1.py
toolsbox/web/__init__.py
toolsbox/web/short_link/__init__.py
toolsbox/web/short_link/t_cn.py
toolsbox-1.18.11.19.2.dist-info/DESCRIPTION.rst
toolsbox-1.18.11.19.2.dist-info/METADATA
toolsbox-1.18.11.19.2.dist-info/RECORD
toolsbox-1.18.11.19.2.dist-info/WHEEL
toolsbox-1.18.11.19.2.dist-info/metadata.json
toolsbox-1.18.11.19.2.dist-info/top_level.txt
