Metadata-Version: 2.0
Name: toolsbox
Version: 1.18.11.19.2
Summary: python工具箱，实用工具，常用代码
Home-page: UNKNOWN
Author: play4fun
Author-email: play4fun@foxmail.com
License: GNU General Public License v3.0
Platform: UNKNOWN
Requires-Dist: requests
Requires-Dist: random-useragent
